quantum_bridge/__init__.py
quantum_bridge/cli.py
quantum_bridge/config.py
quantum_bridge/exceptions.py
quantum_bridge/ir.py
quantum_bridge/backends/__init__.py
quantum_bridge/backends/base.py
quantum_bridge/backends/cirq_backend.py
quantum_bridge/backends/qiskit_backend.py
quantum_bridge/backends/simulator.py
quantum_bridge/execution/__init__.py
quantum_bridge/execution/engine.py
quantum_bridge/execution/fallback.py
quantum_bridge/mitigation/__init__.py
quantum_bridge/mitigation/zne.py
quantum_bridge-1.0.0.dist-info/METADATA
quantum_bridge-1.0.0.dist-info/WHEEL
quantum_bridge-1.0.0.dist-info/entry_points.txt
quantum_bridge-1.0.0.dist-info/licenses/LICENSE
quantum_bridge-1.0.0.dist-info/RECORD
