Metadata-Version: 2.4
Name: quantum-bridge
Version: 1.0.0
Summary: Backend-agnostic bridge for quantum-classical hybrid workflows with auto-fallback and error mitigation
Project-URL: Documentation, https://quantum-bridge.readthedocs.io
Project-URL: Issues, https://github.com/quantum-bridge/quantum-bridge/issues
Author: The Quantum Bridge Contributors
License-Expression: MIT
License-File: LICENSE
Keywords: cirq,error-mitigation,hybrid,qiskit,quantum,quantum-computing,simulator
Classifier: Development Status :: 4 - Beta
Classifier: Intended Audience :: Developers
Classifier: Intended Audience :: Science/Research
Classifier: License :: OSI Approved :: MIT License
Classifier: Operating System :: OS Independent
Classifier: Programming Language :: Python :: 3
Classifier: Programming Language :: Python :: 3.10
Classifier: Programming Language :: Python :: 3.11
Classifier: Programming Language :: Python :: 3.12
Classifier: Topic :: Scientific/Engineering :: Physics
Classifier: Topic :: Software Development :: Libraries :: Python Modules
Requires-Python: >=3.10
Requires-Dist: click>=8.0
Requires-Dist: numpy>=1.24
Requires-Dist: rich>=13.0
Provides-Extra: all
Requires-Dist: cirq>=1.3; extra == 'all'
Requires-Dist: mitiq>=0.30; extra == 'all'
Requires-Dist: qiskit-aer>=0.13; extra == 'all'
Requires-Dist: qiskit-ibm-runtime>=0.20; extra == 'all'
Requires-Dist: qiskit>=1.0; extra == 'all'
Provides-Extra: cirq
Requires-Dist: cirq>=1.3; extra == 'cirq'
Provides-Extra: dev
Requires-Dist: mypy>=1.0; extra == 'dev'
Requires-Dist: pytest-asyncio>=0.21; extra == 'dev'
Requires-Dist: pytest-cov>=4.0; extra == 'dev'
Requires-Dist: pytest>=7.0; extra == 'dev'
Requires-Dist: ruff>=0.1; extra == 'dev'
Provides-Extra: mitiq
Requires-Dist: mitiq>=0.30; extra == 'mitiq'
Provides-Extra: qiskit
Requires-Dist: qiskit-aer>=0.13; extra == 'qiskit'
Requires-Dist: qiskit-ibm-runtime>=0.20; extra == 'qiskit'
Requires-Dist: qiskit>=1.0; extra == 'qiskit'
